setup.py
diagnosticos/__init__.py
diagnosticos/admin.py
diagnosticos/apps.py
diagnosticos/forms.py
diagnosticos/models.py
diagnosticos/tests.py
diagnosticos/urls.py
diagnosticos/views.py
diagnosticos/migrations/0001_initial.py
diagnosticos/migrations/__init__.py
django_pruebas_diagnostico.egg-info/PKG-INFO
django_pruebas_diagnostico.egg-info/SOURCES.txt
django_pruebas_diagnostico.egg-info/dependency_links.txt
django_pruebas_diagnostico.egg-info/requires.txt
django_pruebas_diagnostico.egg-info/top_level.txt