Metadata-Version: 1.1
Name: django-pruebas-diagnostico
Version: 1.2.1.1
Summary: Aplicación sencilla de Django que brinda soporte para pruebas Diagnóstico sencillas.
Home-page: UNKNOWN
Author: Tomás El Fakih
Author-email: tomaselfakih@gmail.com
License: BSD License
Download-URL: https://github.com/scriptom/django-pruebas-diagnostico/archive/1.2.1.1.tar.gz
Platform: UNKNOWN
Classifier: Environment :: Web Environment
Classifier: Framework :: Django
Classifier: Framework :: Django :: 2.1 
Classifier: Intended Audience :: Developers
Classifier: License :: OSI Approved :: BSD License
Classifier: Operating System :: OS Independent
Classifier: Programming Language :: Python
Classifier: Programming Language :: Python :: 3.7
Classifier: Topic :: Internet :: WWW/HTTP
Classifier: Topic :: Internet :: WWW/HTTP :: Dynamic Content
